my_cli_code_explorer/__init__.py
my_cli_code_explorer/main.py
my_cli_code_explorer-0.1.7.dist-info/LICENSE
my_cli_code_explorer-0.1.7.dist-info/METADATA
my_cli_code_explorer-0.1.7.dist-info/WHEEL
my_cli_code_explorer-0.1.7.dist-info/entry_points.txt
my_cli_code_explorer-0.1.7.dist-info/top_level.txt
my_cli_code_explorer-0.1.7.dist-info/RECORD
