Metadata-Version: 2.1
Name: my_cli_code_explorer
Version: 0.1.7
Classifier: Programming Language :: Python :: 3
Classifier: License :: OSI Approved :: MIT License
Classifier: Operating System :: OS Independent
Requires-Python: >=3.9
License-File: LICENSE
Requires-Dist: typer[all]
